rtl/register_file.v
module register_file
#(
  parameter
  DATA_WIDTH = 32, 
  ADDR_WIDTH = 5
)
(
  input clk, 
  input write_en, 
  input [ADDR_WIDTH-1:0] read_addr_1, 
  input [ADDR_WIDTH-1:0] read_addr_2, 
  input [ADDR_WIDTH-1:0] write_addr,
  input [DATA_WIDTH-1:0] write_data, 
  output reg [DATA_WIDTH-1:0] read_data_1, 
  output reg [DATA_WIDTH-1:0] read_data_2
); 
  localparam N_REGS = 1 << ADDR_WIDTH; 
  (* ramstyle = "logic" *) reg [DATA_WIDTH-1:0] file [0:N_REGS-1];

  //sequential write. x0 is hardwired, so writes to it are dropped.
  always@(posedge clk)
  begin 
    if(write_en && write_addr != {ADDR_WIDTH{1'b0}})
      file[write_addr] <= write_data; 
  end 
  
  //combinational read. x0 always reads zero.
  always@(*)
  begin 
    read_data_1 = (read_addr_1 == {ADDR_WIDTH{1'b0}})? {DATA_WIDTH{1'b0}} : file[read_addr_1]; 
    read_data_2 = (read_addr_2 == {ADDR_WIDTH{1'b0}})? {DATA_WIDTH{1'b0}} : file[read_addr_2]; 
  end

  //power-up state. the array itself is never reset: ramstyle="logic" infers
  //distributed RAM, which has no reset port.
  integer i; 
  initial 
  begin 
    for(i = 0; i < N_REGS; i = i+1)
      file[i] = 0; 
  end

endmodule

tb/cocotb/register_file/register_file_dump.vcd
$date
	Sat Aug 22 16:13:56 2026
$end
$version
	Icarus Verilog
$end
$timescale
	1ps
$end
$scope module register_file $end
$var wire 1 ! clk $end
$var wire 5 " read_addr_1 [4:0] $end
$var wire 5 # read_addr_2 [4:0] $end
$var wire 5 $ write_addr [4:0] $end
$var wire 32 % write_data [31:0] $end
$var wire 1 & write_en $end
$var parameter 32 ' ADDR_WIDTH $end
$var parameter 32 ( DATA_WIDTH $end
$var parameter 37 ) N_REGS $end
$var reg 32 * read_data_1 [31:0] $end
$var reg 32 + read_data_2 [31:0] $end
$var integer 32 , i [31:0] $end
$upscope $end
$enddefinitions $end
$comment Show the parameter values. $end
$dumpall
b100000 )
b100000 (
b101 '
$end
#0
$dumpvars
b100000 ,
bx +
bx *
z&
bz %
bz $
bz #
bz "
1!
$end
#500
b0 +
b0 *
b11011101110000110111001001111001 %
b1011 $
b11010 #
b10 "
1&
0!
#1000
1!
#1500
b1101000100110001011111010000000 %
b11010 $
b110 #
b11000 "
0!
#2000
1!
#2500
b11111110101111001001111101111101 %
b0 $
b11001 #
b10100 "
0&
0!
#3000
1!
#3500
b110011001000000000000110111000 %
b11100 $
b0 #
b1110 "
1&
0!
#4000
1!
#4500
b11110101000110010100111111111000 %
b10001 $
b11001 #
b1101 "
0&
0!
#5000
1!
#5500
b11000100000100000000110111000101 %
b100 $
b11011 "
1&
0!
#6000
1!
#6500
b1000011101001001000101010011011 %
b1001 $
b11000 #
b10 "
0&
0!
#7000
1!
#7500
b1111000000110111111000101101100 %
b10001 $
b10101 #
b10110 "
0!
#8000
1!
#8500
b11000011011101100101110110000010 %
b1010 $
b1111 #
b110 "
1&
0!
#9000
1!
#9500
b1000111010111000011100000100000 %
b11 $
b10110 #
b11 "
0&
0!
#10000
1!
#10500
b11000010110110100001001000110100 %
b10101 $
b1000 #
b10000 "
0!
#11000
1!
#11500
b110111100001100001110110001101 %
b11000 #
b11111 "
0!
#12000
1!
#12500
b1001001111111000101010110000101 %
b11 $
b10001 #
b10111 "
0!
#13000
1!
#13500
b11110011000010010101101011111011 %
b1000 $
b1110 #
b11000 "
0!
#14000
1!
#14500
b111100101001101100001101001000 %
b111 $
b10000 #
b10110 "
0!
#15000
1!
#15500
b11000101101100011001111101111100 %
b10101 $
b10010 #
b11001 "
1&
0!
#16000
1!
#16500
b10010100010010011111010101010011 %
b10111 $
b1 #
b10000 "
0!
#17000
1!
#17500
b11000100000100000000110111000101 +
b11000100000100000000110111000101 *
b10011000101011010001001111111110 %
b100 #
b100 "
0&
0!
#18000
1!
#18500
b0 +
b1101000100110001011111010000000 *
b11110010011100000010010110000000 %
b11110 $
b111 #
b11010 "
0!
#19000
1!
#19500
b0 *
b1100111000100001111001101011110 %
b11000 $
b11 #
b1110 "
1&
0!
#20000
1!
#20500
b10100000101010001110000001011101 %
b1010 $
b1110 #
b10000 "
0!
#21000
1!
#21500
b11000101101100011001111101111100 +
b11011101110000110111001001111001 *
b11110100101011011100000101000011 %
b11 $
b10101 #
b1011 "
0!
#22000
1!
#22500
b0 +
b0 *
b110100001110110111000111110011 %
b10011 $
b10100 #
b101 "
0!
#23000
1!
#23500
b10110011110011100001010111100001 %
b11101 $
b1111 #
b11101 "
0!
#24000
b10110011110011100001010111100001 *
1!
#24500
b0 *
b111000101110111101101000110000 %
b11111 $
b11011 #
b11001 "
0&
0!
#25000
1!
#25500
b11001110010100110010110001011110 %
b111 $
b10010 #
b10100 "
0!
#26000
1!
#26500
b1001111000001000110010000000100 %
b10 #
b1100 "
1&
0!
#27000
1!
#27500
b1100111000100001111001101011110 +
b1101000100110001011111010000000 *
b10100010001111011101111010001 %
b1 $
b11000 #
b11010 "
0!
#28000
1!
#28500
b0 +
b0 *
b1100000000100001110101110001 %
b100 $
b10010 #
b10001 "
0&
0!
#29000
1!
#29500
b10101101010000001111101100101001 %
b10001 $
b10100 #
b1110 "
1&
0!
#30000
1!
#30500
b11110110100101001010100110010111 %
b10010 #
0&
0!
#31000
1!
#31500
b10101101010000001111101100101001 +
b1001111000001000110010000000100 *
b1011011010010110001001011011111 %
b1011 $
b10001 #
b111 "
1&
0!
#32000
1!
#32500
b0 +
b0 *
b10000100111111111000011000111011 %
b1001 $
b10 #
b10 "
0!
#33000
1!
#33500
b10101101010000001111101100101001 +
b10101101010000001111101100101001 *
b1000010001011100101010111111110 %
b11010 $
b10001 #
b10001 "
0&
0!
#34000
1!
#34500
b0 +
b110011001000000000000110111000 *
b11111110001001011010110100010101 %
b1110 $
b11001 #
b11100 "
0!
#35000
1!
#35500
b10000100111111111000011000111011 +
b0 *
b111000001011101011100101101010 %
b11001 $
b1001 #
b10 "
0!
#36000
1!
#36500
b110100001110110111000111110011 +
b101001110011011110011000001001 %
b11110 $
b10011 #
b11011 "
1&
0!
#37000
1!
#37500
b0 +
b1101000100110001011111010000000 *
b11101110100111011010011001000010 %
b1010 $
b0 #
b11010 "
0!
#38000
1!
#38500
b1011011010010110001001011011111 +
b0 *
b11001111000001001101000001001100 %
b110 $
b1011 #
b1000 "
0&
0!
#39000
1!
#39500
b0 +
b100000100101110100111111101011 %
b11110 $
b1101 #
b10100 "
0!
#40000
1!
#40500
b10100011111001011011110011011111 %
b10100 $
b11111 #
b101 "
1&
0!
#41000
1!
#41500
b1100111000100001111001101011110 *
b10101100001110111000111001010 %
b1001 $
b110 #
b11000 "
0&
0!
#42000
1!
#42500
b0 *
b10011000001111011110100101001111 %
b10011 $
b1000 #
b10110 "
0!
#43000
1!
#43500
b1011011010010110001001011011111 *
b100110010111000101100011001101 %
b10000 $
b1101 #
b1011 "
0!
#44000
1!
#44500
b0 *
b100000111101010111001101111101 %
b11100 $
b11111 #
b10 "
1&
0!
#45000
1!
#45500
b10010101100111100010010010011101 %
b1000 $
b11011 #
b11111 "
0!
#46000
1!
#46500
b10100010001111011101111010001 +
b1000001111010101011101000001011 %
b11111 $
b1 #
b1110 "
0&
0!
#47000
1!
#47500
b1001111000001000110010000000100 +
b100000111101010111001101111101 *
b11101010011100100101101010011001 %
b11101 $
b111 #
b11100 "
1&
0!
#48000
1!
#48500
b1101000100110001011111010000000 +
b11000101101100011001111101111100 *
b1001001011100010110010000010010 %
b101 $
b11010 #
b10101 "
0!
#49000
1!
#49500
b10100010001111011101111010001 +
b1100111000100001111001101011110 *
b10001010101001110011100111111011 %
b1 #
b11000 "
0&
0!
#50000
1!
#50500
b0 +
b10101101111100001101110001110000 %
b10001 $
b11011 #
1&
0!
#51000
1!
#51500
b10000100111111111000011000111011 +
b0 *
b11111110011101100010111010101101 %
b1 $
b1001 #
b110 "
0!
#52000
1!
#52500
b11101010011100100101101010011001 +
b1011011010010110001001011011111 *
b10110000001011111000011001011110 %
b1001 $
b11101 #
b1011 "
0&
0!
#53000
1!
#53500
b10000100111111111000011000111011 +
b0 *
b11010100011100011100100011001111 %
b1101 $
b1001 #
b1110 "
0!
#54000
1!
#54500
b0 +
b101001000111010000010011011000 %
b11111 $
b1101 #
b1111 "
1&
0!
#55000
1!
#55500
b11000101101100011001111101111100 +
b11111110011101100010111010101101 *
b10100100111111111000100110001000 %
b10101 #
b1 "
0!
#56000
1!
#56500
b11000100000100000000110111000101 +
b10101101111100001101110001110000 *
b101101011111011111000010100001 %
b100 $
b100 #
b10001 "
0&
0!
#57000
1!
#57500
b10101101111100001101110001110000 +
b11000100000100000000110111000101 *
b10011010011110001001110111101100 %
b11100 $
b10001 #
b100 "
1&
0!
#58000
1!
#58500
b0 +
b10010100010010011111010101010011 *
b10101100110110001110111110010111 %
b10 $
b10000 #
b10111 "
0!
#59000
1!
#59500
b11000101101100011001111101111100 *
b10110011011111101111111101011 %
b10111 $
b11001 #
b10101 "
0&
0!
#60000
1!
#60500
b10100100111111111000100110001000 +
b11101010011100100101101010011001 *
b1001011001000011011011110011111 %
b11011 $
b11111 #
b11101 "
1&
0!
#61000
1!
#61500
b11000101101100011001111101111100 +
b10010100010010011111010101010011 *
b10101011101010111111101100010100 %
b11100 $
b10101 #
b10111 "
0&
0!
#62000
1!
#62500
b0 +
b1011011010010110001001011011111 *
b11001100110011000101001111011010 %
b111 $
b1101 #
b1011 "
1&
0!
#63000
1!
#63500
b101001110011011110011000001001 *
b1101100110101001010110000001101 %
b11100 $
b11110 "
0&
0!
#64000
1!
#64500
b0 *
b1111101010110111110100100001110 %
b11 $
b1101 "
0!
#65000
1!
#65500
b1101000100110001011111010000000 +
b11101110100111011010011001000010 *
b10100110000000110110000111111 %
b10000 $
b11010 #
b1010 "
1&
0!
#66000
1!
#66500
b11101110100111011010011001000010 +
b10011010011110001001110111101100 *
b11110010011100010001011110100010 %
b1111 $
b1010 #
b11100 "
0&
0!
#67000
1!
#67500
b1001001011100010110010000010010 +
b1011011010010110001001011011111 *
b11011000110011000111010110100010 %
b1010 $
b101 #
b1011 "
1&
0!
#68000
1!
#68500
b11011000110011000111010110100010 +
b10101100110110001110111110010111 *
b11100110010011010011000100101 %
b0 $
b1010 #
b10 "
0&
0!
#69000
1!
#69500
b0 +
b0 *
b10111010001100011110011010110 %
b11000 $
b0 #
b1111 "
1&
0!
#70000
1!
#70500
b11110100101011011100000101000011 +
b11001011011101001110111101010001 %
b1010 $
b11 #
b11001 "
0!
#71000
1!
#71500
b10101100110110001110111110010111 +
b10000101110101100111100101111000 %
b10101 $
b10 #
b110 "
0!
#72000
1!
#72500
b10111010001100011110011010110 +
b10100110110010001001011111010001 %
b1101 $
b11000 #
b1110 "
0&
0!
#73000
1!
#73500
b10010100010010011111010101010011 +
b11000100000100000000110111000101 *
b1110101011001000010001011111000 %
b1011 $
b10111 #
b100 "
0!
#74000
1!
#74500
b0 +
b10000101110101100111100101111000 *
b11101011000011000011001101001100 %
b11100 $
b10110 #
b10101 "
1&
0!
#75000
1!
#75500
b0 *
b11111011011110000011110011110000 %
b11 $
b1110 #
b1111 "
0!
#76000
1!
#76500
b11001011011101001110111101010001 *
b11110111100101000101110001001110 %
b10111 $
b10110 #
b1010 "
0!
#77000
1!
#77500
b1001001011100010110010000010010 +
b11001100110011000101001111011010 *
b1001000011000010101010111111010 %
b101 #
b111 "
0&
0!
#78000
1!
#78500
b11101011000011000011001101001100 +
b0 *
b10010000101000001111111001011000 %
b1100 $
b11100 #
b10010 "
1&
0!
#79000
1!
#79500
b10100110000000110110000111111 +
b10000101110101100111100101111000 *
b10010101001011011100101100010100 %
b1000 $
b10000 #
b10101 "
0&
0!
#80000
1!
#80500
b101001110011011110011000001001 +
b101001110011011110011000001001 *
b11000110100111011110110011010100 %
b0 $
b11110 #
b11110 "
0!
#81000
1!
#81500
b11000100000100000000110111000101 +
b0 *
b11111100100101011010001111101111 %
b11101 $
b100 #
b1101 "
1&
0!
#82000
1!
#82500
b0 +
b1001001011100010110010000010010 *
b101011110011101100100011111011 %
b11110 $
b1111 #
b101 "
0&
0!
#83000
1!
#83500
b1101000100110001011111010000000 *
b11111101100111101111100100111100 %
b111 $
b10110 #
b11010 "
1&
0!
#84000
1!
#84500
b10100011111001011011110011011111 *
b11110000111100000110010000100000 %
b1 $
b1111 #
b10100 "
0&
0!
#85000
1!
#85500
b0 *
b1110000000101010110010100000001 %
b11 $
b1110 #
b10110 "
0!
#86000
1!
#86500
b1001001011100010110010000010010 +
b11111011011110000011110011110000 *
b10101001001110001000100110011011 %
b10 $
b101 #
b11 "
0!
#87000
1!
#87500
b10010000101000001111111001011000 +
b10000100111111111000011000111011 *
b10010010111001100010100000111 %
b11010 $
b1100 #
b1001 "
1&
0!
#88000
1!
#88500
b11111101100111101111100100111100 +
b10111010001100011110011010110 *
b1010110100001000101111110000 %
b11100 $
b111 #
b11000 "
0!
#89000
1!
#89500
b10000100111111111000011000111011 +
b10010010111001100010100000111 *
b11111001001101101001100111110100 %
b100 $
b1001 #
b11010 "
0!
#90000
1!
#90500
b10000101110101100111100101111000 +
b0 *
b1001110101111101011010010111010 %
b10111 $
b10101 #
b1101 "
0!
#91000
1!
#91500
b10100011111001011011110011011111 +
b11000100010110001000010001011101 %
b101 $
b10100 #
b11001 "
0!
#92000
1!
#92500
b110100001110110111000111110011 +
b10010010111001100010100000111 *
b1110100001010100111010101010101 %
b1011 $
b10011 #
b11010 "
0!
#93000
1!
#93500
b1110100001010100111010101010101 +
b10010000101000001111111001011000 *
b11010100111000011011010010101111 %
b10011 $
b1011 #
b1100 "
0!
#94000
1!
#94500
b101001110011011110011000001001 +
b1010110100001000101111110000 *
b1011100001010110100111100111 %
b10111 $
b11110 #
b11100 "
0&
0!
#95000
1!
#95500
b10101100110110001110111110010111 +
b10000100111111111000011000111011 *
b101010010101100100101011100 %
b11011 $
b10 #
b1001 "
0!
#96000
1!
#96500
b11001011011101001110111101010001 +
b11111101100111101111100100111100 *
b1011001100010110000101101001110 %
b1 $
b1010 #
b111 "
0!
#97000
1!
#97500
b11111011011110000011110011110000 +
b10000101110101100111100101111000 *
b11110000010111001000000001011111 %
b110 $
b11 #
b10101 "
0!
#98000
1!
#98500
b11001011011101001110111101010001 +
b10100011111001011011110011011111 *
b11001000110110001101101100011111 %
b1000 $
b1010 #
b10100 "
1&
0!
#99000
1!
#99500
b101001110011011110011000001001 +
b11111001001101101001100111110100 *
b10000101100010000101111010001000 %
b1001 $
b11110 #
b100 "
0&
0!
